harbor/__init__.py
harbor/test_utils.py
harbor/adapters/__init__.py
harbor/adapters/python/__init__.py
harbor/adapters/python/parser.py
harbor/cli/__init__.py
harbor/cli/main.py
harbor/core/__init__.py
harbor/core/audit.py
harbor/core/ddt.py
harbor/core/decorator.py
harbor/core/diary.py
harbor/core/drafting.py
harbor/core/git_utils.py
harbor/core/index.py
harbor/core/init.py
harbor/core/l2.py
harbor/core/storage.py
harbor/core/sync.py
harbor/core/t_decorate.py
harbor/core/utils.py
harbor/utils/__init__.py
harbor/utils/formatting.py
harbor/utils/i18n.py
harbor_spec-1.2.6.dist-info/licenses/LICENSE
harbor_spec-1.2.6.dist-info/METADATA
harbor_spec-1.2.6.dist-info/WHEEL
harbor_spec-1.2.6.dist-info/entry_points.txt
harbor_spec-1.2.6.dist-info/top_level.txt
harbor_spec-1.2.6.dist-info/RECORD
