Metadata-Version: 2.4
Name: harbor-spec
Version: 1.2.6
Summary: Harbor-spec v1.0.2 reference implementation (Python-only)
License: MIT License
Requires-Python: >=3.9
License-File: LICENSE
Requires-Dist: pyyaml
Requires-Dist: openai>=1.0.0
Requires-Dist: python-dotenv>=1.0.0
Requires-Dist: rich>=13.7
Requires-Dist: pathspec>=0.11.0
Provides-Extra: dev
Requires-Dist: pytest; extra == "dev"
Dynamic: license-file
